[
  {
    "date_stolen": 1693309949,
    "description": null,
    "frame_colors": [
      "Teal",
      "Yellow or Gold",
      "Red"
    ],
    "frame_model": "BuzGHiOsq81",
    "id": 1649620,
    "is_stock_img": false,
    "large_img": null,
    "location_found": null,
    "manufacturer_name": "Gef7p8RuhVEB66Z7GTzY",
    "external_id": null,
    "registry_name": null,
    "registry_url": null,
    "serial": "SNNXD2uO1KehWZ",
    "status": "stolen",
    "stolen": true,
    "stolen_coordinates": null,
    "stolen_location": "D Z0fk Uvlf2 Ua Buqep Xl T, ALDO7126@HOTMAIL.COM, AN",
    "thumb": null,
    "title": "1923 Gef7p8RuhVEB66Z7GTzY BuzGHiOsq81 wheelchair",
    "url": "https://bikeindex.org/bikes/1649620",
    "year": 1923
  },
  {
    "date_stolen": 1693308854,
    "description": null,
    "frame_colors": [
      "Blue",
      "Yellow or Gold",
      "Red"
    ],
    "frame_model": "gkS3GmGdOkXuQb",
    "id": 1649617,
    "is_stock_img": false,
    "large_img": null,
    "location_found": null,
    "manufacturer_name": "9IOqDeYTBo9",
    "external_id": null,
    "registry_name": null,
    "registry_url": null,
    "serial": "V8wV6SAN7l",
    "status": "stolen",
    "stolen": true,
    "stolen_coordinates": [
      32.35,
      -89.4
    ],
    "stolen_location": "V Yxk6 Hy8 A7 G Tj5x Hc5, MS DALLASDANCE06@GMAIL.COM, MS",
    "thumb": null,
    "title": "1968 9IOqDeYTBo9 gkS3GmGdOkXuQb wheelchair",
    "url": "https://bikeindex.org/bikes/1649617",
    "year": 1968
  },
  {
    "date_stolen": 1693305394,
    "description": null,
    "frame_colors": [
      "Purple",
      "Black",
      "White"
    ],
    "frame_model": "LHU4sviwaNdyPogkSWXF",
    "id": 1649613,
    "is_stock_img": false,
    "large_img": null,
    "location_found": null,
    "manufacturer_name": "oNWodNUgdgD7nBYOXi",
    "external_id": null,
    "registry_name": null,
    "registry_url": null,
    "serial": "BUYjoOdGksFIA",
    "status": "stolen",
    "stolen": true,
    "stolen_coordinates": null,
    "stolen_location": "2 Ywjvvb N Jpk V Ik3, JRCINCY280@GMAIL.COM, SJ",
    "thumb": null,
    "title": "1991 oNWodNUgdgD7nBYOXi LHU4sviwaNdyPogkSWXF pedi cab (rickshaw)",
    "url": "https://bikeindex.org/bikes/1649613",
    "year": 1991
  },
  {
    "date_stolen": 1693305033,
    "description": null,
    "frame_colors": [
      "Orange",
      "Blue",
      "Yellow or Gold"
    ],
    "frame_model": "LgEroNXeKZzbDmybAWTQ",
    "id": 1649612,
    "is_stock_img": false,
    "large_img": null,
    "location_found": null,
    "manufacturer_name": "IrQjc3go7jV9",
    "external_id": null,
    "registry_name": null,
    "registry_url": null,
    "serial": "IozADxqtkSXTRI",
    "status": "stolen",
    "stolen": true,
    "stolen_coordinates": [
      34.05,
      -111.09
    ],
    "stolen_location": "Jbj Se Tv Any Eo Gtahw, AZ LPAN@PAG.COM, AZ",
    "thumb": null,
    "title": "1944 IrQjc3go7jV9 LgEroNXeKZzbDmybAWTQ tricycle",
    "url": "https://bikeindex.org/bikes/1649612",
    "year": 1944
  },
  {
    "date_stolen": 1693304144,
    "description": null,
    "frame_colors": [
      "Brown",
      "Yellow or Gold",
      "Silver, gray or bare metal"
    ],
    "frame_model": "oEsOFooMvfN23ly",
    "id": 1649611,
    "is_stock_img": false,
    "large_img": null,
    "location_found": null,
    "manufacturer_name": "ZvEDkheWSsVyRLKJGbi",
    "external_id": null,
    "registry_name": null,
    "registry_url": null,
    "serial": "D3lF3OeQ7g",
    "status": "stolen",
    "stolen": true,
    "stolen_coordinates": null,
    "stolen_location": "W Pyit2 Vb Ebd, JACOB.GRUENWALD@YAHOO.COM, GR",
    "thumb": null,
    "title": "1947 ZvEDkheWSsVyRLKJGbi oEsOFooMvfN23ly penny farthing",
    "url": "https://bikeindex.org/bikes/1649611",
    "year": 1947
  },
  {
    "date_stolen": 1693304142,
    "description": null,
    "frame_colors": [
      "Brown",
      "Yellow or Gold",
      "Silver, gray or bare metal"
    ],
    "frame_model": "oEsOFooMvfN23ly",
    "id": 1649610,
    "is_stock_img": false,
    "large_img": null,
    "location_found": null,
    "manufacturer_name": "ZvEDkheWSsVyRLKJGbi",
    "external_id": null,
    "registry_name": null,
    "registry_url": null,
    "serial": "D3lF3OeQ7g",
    "status": "stolen",
    "stolen": true,
    "stolen_coordinates": null,
    "stolen_location": "W Pyit2 Vb Ebd, JACOB.GRUENWALD@YAHOO.COM, GR",
    "thumb": null,
    "title": "1947 ZvEDkheWSsVyRLKJGbi oEsOFooMvfN23ly penny farthing",
    "url": "https://bikeindex.org/bikes/1649610",
    "year": 1947
  },
  {
    "date_stolen": 1693302449,
    "description": null,
    "frame_colors": [
      "Orange",
      "Black",
      "Brown"
    ],
    "frame_model": "NfxaBr6RKHAw",
    "id": 1649609,
    "is_stock_img": false,
    "large_img": null,
    "location_found": null,
    "manufacturer_name": "Fst60DMfTE6fSKf33vZ",
    "external_id": null,
    "registry_name": null,
    "registry_url": null,
    "serial": "Vz2Mgbo3AjRM4Cr",
    "status": "stolen",
    "stolen": true,
    "stolen_coordinates": [
      -13.13,
      27.85
    ],
    "stolen_location": "7 Vh An L4 Vn Nn, TISHAVARGHESE6@GMAIL.COM, ZM",
    "thumb": null,
    "title": "2002 Fst60DMfTE6fSKf33vZ NfxaBr6RKHAw tandem",
    "url": "https://bikeindex.org/bikes/1649609",
    "year": 2002
  },
  {
    "date_stolen": 1693300363,
    "description": null,
    "frame_colors": [
      "Green",
      "White",
      "White"
    ],
    "frame_model": "3kmGeYFJ8Ek",
    "id": 1649604,
    "is_stock_img": false,
    "large_img": null,
    "location_found": null,
    "manufacturer_name": "J9cYD2qsRLN",
    "external_id": null,
    "registry_name": null,
    "registry_url": null,
    "serial": "ZK1vgJLRkYHiPOUHv",
    "status": "stolen",
    "stolen": true,
    "stolen_coordinates": null,
    "stolen_location": "Cn Mh1 A7 I Fqi3, KCHENG_99@YAHOO.COM, VC",
    "thumb": null,
    "title": "1999 J9cYD2qsRLN 3kmGeYFJ8Ek scooter (not electric)",
    "url": "https://bikeindex.org/bikes/1649604",
    "year": 1999
  },
  {
    "date_stolen": 1693300087,
    "description": null,
    "frame_colors": [
      "Teal",
      "Silver, gray or bare metal",
      "Green"
    ],
    "frame_model": "gRCphy591LEoOoMRp",
    "id": 1649602,
    "is_stock_img": false,
    "large_img": null,
    "location_found": null,
    "manufacturer_name": "hBYYOZxUlB53zjpdC1X",
    "external_id": null,
    "registry_name": null,
    "registry_url": null,
    "serial": "SlZ9V2o2YR4uvD9g",
    "status": "stolen",
    "stolen": true,
    "stolen_coordinates": null,
    "stolen_location": "Ln Vw Oxz Rs Pk4f Av, LPAN@PAG.COM, HR",
    "thumb": null,
    "title": "1941 hBYYOZxUlB53zjpdC1X gRCphy591LEoOoMRp tricycle",
    "url": "https://bikeindex.org/bikes/1649602",
    "year": 1941
  },
  {
    "date_stolen": 1693299515,
    "description": null,
    "frame_colors": [
      "White",
      "Black",
      "Silver, gray or bare metal"
    ],
    "frame_model": "VJWDH89LqY7wp39e",
    "id": 1649601,
    "is_stock_img": false,
    "large_img": null,
    "location_found": null,
    "manufacturer_name": "s6ubHygmh9CV82dU",
    "external_id": null,
    "registry_name": null,
    "registry_url": null,
    "serial": "yV7YvGvBEprIlrTVSFhT",
    "status": "stolen",
    "stolen": true,
    "stolen_coordinates": null,
    "stolen_location": "Prj Serrp F21l2 Ao, RLUCKHARDT@GMAIL.COM, BH",
    "thumb": null,
    "title": "2014 s6ubHygmh9CV82dU VJWDH89LqY7wp39e tricycle",
    "url": "https://bikeindex.org/bikes/1649601",
    "year": 2014
  },
  {
    "date_stolen": 1693298973,
    "description": null,
    "frame_colors": [
      "Yellow or Gold",
      "Brown",
      "Yellow or Gold"
    ],
    "frame_model": "YzqkScHQr5",
    "id": 1649600,
    "is_stock_img": false,
    "large_img": null,
    "location_found": null,
    "manufacturer_name": "8pKu9vl2jeqry02auj",
    "external_id": null,
    "registry_name": null,
    "registry_url": null,
    "serial": "8NNwDrMXWeNmGMfC",
    "status": "stolen",
    "stolen": true,
    "stolen_coordinates": null,
    "stolen_location": "Hy0m M Lh5xj Bc21 Ysj, LPAN@PAG.COM, TO",
    "thumb": null,
    "title": "1973 8pKu9vl2jeqry02auj YzqkScHQr5 tandem",
    "url": "https://bikeindex.org/bikes/1649600",
    "year": 1973
  },
  {
    "date_stolen": 1693297734,
    "description": null,
    "frame_colors": [
      "Brown",
      "Black",
      "White"
    ],
    "frame_model": "KuOR3Qr0FX",
    "id": 1649599,
    "is_stock_img": false,
    "large_img": null,
    "location_found": null,
    "manufacturer_name": "rsQ28ra50xoLzd2btLb",
    "external_id": null,
    "registry_name": null,
    "registry_url": null,
    "serial": "Rg0GFeGWVVrg8",
    "status": "stolen",
    "stolen": true,
    "stolen_coordinates": null,
    "stolen_location": "Xal1x Qrhflh Ts2 L9, LPAN@PAG.COM, LI",
    "thumb": null,
    "title": "1935 rsQ28ra50xoLzd2btLb KuOR3Qr0FX",
    "url": "https://bikeindex.org/bikes/1649599",
    "year": 1935
  },
  {
    "date_stolen": 1693296466,
    "description": null,
    "frame_colors": [
      "Red",
      "Black"
    ],
    "frame_model": "Cc47",
    "id": 1649598,
    "is_stock_img": false,
    "large_img": "https://files.bikeindex.org/uploads/Pu/740879/large_Screenshot_20230829-014050.png",
    "location_found": null,
    "manufacturer_name": "Ebgo",
    "external_id": null,
    "registry_name": null,
    "registry_url": null,
    "serial": "c47ed2414eb2598",
    "status": "stolen",
    "stolen": true,
    "stolen_coordinates": [
      53.55,
      -113.48
    ],
    "stolen_location": "Edmonton, T5H 2H6, CA",
    "thumb": "https://files.bikeindex.org/uploads/Pu/740879/small_Screenshot_20230829-014050.png",
    "title": "2021 Ebgo Cc47",
    "url": "https://bikeindex.org/bikes/1649598",
    "year": 2021
  },
  {
    "date_stolen": 1693294468,
    "description": null,
    "frame_colors": [
      "Blue",
      "Teal",
      "Teal"
    ],
    "frame_model": "hV1EnR40tQ5bhxo4IK1e",
    "id": 1649597,
    "is_stock_img": false,
    "large_img": null,
    "location_found": null,
    "manufacturer_name": "MXsqDPFjEDGfph9F",
    "external_id": null,
    "registry_name": null,
    "registry_url": null,
    "serial": "2za5kHorxA3vZfbJTqQD",
    "status": "stolen",
    "stolen": true,
    "stolen_coordinates": null,
    "stolen_location": "Ns Bfdrqc Ndl Hqi Jn Xf, SUNYAN2008@GMAIL.COM, PW",
    "thumb": null,
    "title": "1992 MXsqDPFjEDGfph9F hV1EnR40tQ5bhxo4IK1e cargo tricycle (front storage)",
    "url": "https://bikeindex.org/bikes/1649597",
    "year": 1992
  },
  {
    "date_stolen": 1693292941,
    "description": null,
    "frame_colors": [
      "Orange",
      "Teal",
      "Blue"
    ],
    "frame_model": "gvpf0oTYztp54ml",
    "id": 1649593,
    "is_stock_img": false,
    "large_img": null,
    "location_found": null,
    "manufacturer_name": "V3tGs7dHOx",
    "external_id": null,
    "registry_name": null,
    "registry_url": null,
    "serial": "SjGLRZuYZ3U4kvQ",
    "status": "stolen",
    "stolen": true,
    "stolen_coordinates": null,
    "stolen_location": "B4 Cd4cfe V20l Ki5 Ms2 Sc, RLUCKHARDT@GMAIL.COM, GD",
    "thumb": null,
    "title": "1973 V3tGs7dHOx gvpf0oTYztp54ml bike trailer",
    "url": "https://bikeindex.org/bikes/1649593",
    "year": 1973
  },
  {
    "date_stolen": 1693291304,
    "description": "Kona handle bars lsx crank purple peddals fox front and rear shocks avid elixer brakes ",
    "frame_colors": [
      "Blue"
    ],
    "frame_model": "Reign 1",
    "id": 1555585,
    "is_stock_img": false,
    "large_img": "https://bikebook.s3.amazonaws.com/uploads/Fr/8103/Reign_1_blue_GE_GA_GU_72dpiWIDE.jpg",
    "location_found": null,
    "manufacturer_name": "Giant",
    "external_id": null,
    "registry_name": null,
    "registry_url": null,
    "serial": "GL997897",
    "status": "stolen",
    "stolen": true,
    "stolen_coordinates": [
      51.04,
      -114.07
    ],
    "stolen_location": "Calgary, CA",
    "thumb": "https://bikebook.s3.amazonaws.com/uploads/Fr/8103/small_Reign_1_blue_GE_GA_GU_72dpiWIDE.jpg",
    "title": "2010 Giant Reign 1",
    "url": "https://bikeindex.org/bikes/1555585",
    "year": 2010
  },
  {
    "date_stolen": 1693291139,
    "description": null,
    "frame_colors": [
      "Green",
      "Stickers tape or other cover-up"
    ],
    "frame_model": "HGYvy8YH4KAd7DMl",
    "id": 1649586,
    "is_stock_img": false,
    "large_img": null,
    "location_found": null,
    "manufacturer_name": "4kCzVxyztO",
    "external_id": null,
    "registry_name": null,
    "registry_url": null,
    "serial": "IrgkxtJNxBLRHRQz",
    "status": "stolen",
    "stolen": true,
    "stolen_coordinates": null,
    "stolen_location": "1 Gt Fd9qg H Lxs1 Cc Ft29, DONALD.LUNDY12@GMAIL.COM, BA",
    "thumb": null,
    "title": "1955 4kCzVxyztO HGYvy8YH4KAd7DMl wheelchair",
    "url": "https://bikeindex.org/bikes/1649586",
    "year": 1955
  },
  {
    "date_stolen": 1693287239,
    "description": null,
    "frame_colors": [
      "Green",
      "White",
      "Black"
    ],
    "frame_model": "WlpqYucj0Ua",
    "id": 1649578,
    "is_stock_img": false,
    "large_img": null,
    "location_found": null,
    "manufacturer_name": "Ym1biq57jReCSa",
    "external_id": null,
    "registry_name": null,
    "registry_url": null,
    "serial": "RXnv7w1zWA1LTE0c",
    "status": "stolen",
    "stolen": true,
    "stolen_coordinates": [
      19.41,
      -99.16
    ],
    "stolen_location": "O25 Fop Drev Nn, LPAN@PAG.COM, NG",
    "thumb": null,
    "title": "1982 Ym1biq57jReCSa WlpqYucj0Ua recumbent",
    "url": "https://bikeindex.org/bikes/1649578",
    "year": 1982
  },
  {
    "date_stolen": 1693285430,
    "description": null,
    "frame_colors": [
      "Teal",
      "Orange",
      "Orange"
    ],
    "frame_model": "uQ95SUOCaf",
    "id": 1649569,
    "is_stock_img": false,
    "large_img": null,
    "location_found": null,
    "manufacturer_name": "GmPBeNpgJL",
    "external_id": null,
    "registry_name": null,
    "registry_url": null,
    "serial": "9ek37KJ0VzyQ0",
    "status": "stolen",
    "stolen": true,
    "stolen_coordinates": null,
    "stolen_location": "N F Vq H Uv3 Ff Bs, CHRISTHEIS@YAHOO.COM, PL",
    "thumb": null,
    "title": "1997 GmPBeNpgJL uQ95SUOCaf unicycle",
    "url": "https://bikeindex.org/bikes/1649569",
    "year": 1997
  },
  {
    "date_stolen": 1693285200,
    "description": null,
    "frame_colors": [
      "White",
      "Purple",
      "Brown"
    ],
    "frame_model": "y1506tBkhh4Kfp",
    "id": 1649332,
    "is_stock_img": false,
    "large_img": null,
    "location_found": null,
    "manufacturer_name": "hxxxSqAc8JKahnFfEJ",
    "external_id": null,
    "registry_name": null,
    "registry_url": null,
    "serial": "itBSgeNXq67sgzNVFAQc",
    "status": "stolen",
    "stolen": true,
    "stolen_coordinates": null,
    "stolen_location": "Acz Dt Yhtx L El S78 Qu, LSVECELLIO1@BELLSOUTH.NET, MV",
    "thumb": null,
    "title": "1933 hxxxSqAc8JKahnFfEJ y1506tBkhh4Kfp recumbent",
    "url": "https://bikeindex.org/bikes/1649332",
    "year": 1933
  },
  {
    "date_stolen": 1693283572,
    "description": null,
    "frame_colors": [
      "Blue",
      "Pink",
      "Orange"
    ],
    "frame_model": "dBbCsE3iLPgDot",
    "id": 1649503,
    "is_stock_img": false,
    "large_img": null,
    "location_found": null,
    "manufacturer_name": "8ZjPrq36rfBgpXa",
    "external_id": null,
    "registry_name": null,
    "registry_url": null,
    "serial": "BAJt1oOPBN",
    "status": "stolen",
    "stolen": true,
    "stolen_coordinates": null,
    "stolen_location": "Ytzw7 My9u, LPAN@PAG.COM, PM",
    "thumb": null,
    "title": "1901 8ZjPrq36rfBgpXa dBbCsE3iLPgDot unicycle",
    "url": "https://bikeindex.org/bikes/1649503",
    "year": 1901
  },
  {
    "date_stolen": 1693283568,
    "description": null,
    "frame_colors": [
      "Blue",
      "Pink",
      "Orange"
    ],
    "frame_model": "dBbCsE3iLPgDot",
    "id": 1649502,
    "is_stock_img": false,
    "large_img": null,
    "location_found": null,
    "manufacturer_name": "8ZjPrq36rfBgpXa",
    "external_id": null,
    "registry_name": null,
    "registry_url": null,
    "serial": "BAJt1oOPBN",
    "status": "stolen",
    "stolen": true,
    "stolen_coordinates": null,
    "stolen_location": "Ytzw7 My9u, LPAN@PAG.COM, PM",
    "thumb": null,
    "title": "1901 8ZjPrq36rfBgpXa dBbCsE3iLPgDot unicycle",
    "url": "https://bikeindex.org/bikes/1649502",
    "year": 1901
  },
  {
    "date_stolen": 1693283309,
    "description": null,
    "frame_colors": [
      "Brown",
      "Red",
      "Yellow or Gold"
    ],
    "frame_model": "EZnuSYCNle7JcI",
    "id": 1649500,
    "is_stock_img": false,
    "large_img": null,
    "location_found": null,
    "manufacturer_name": "6DyK6aH3j1POwRDq4h",
    "external_id": null,
    "registry_name": null,
    "registry_url": null,
    "serial": "PcxvnBd5ATX05gAO",
    "status": "stolen",
    "stolen": true,
    "stolen_coordinates": null,
    "stolen_location": "0 R4 Zuap5 O1x Kh, SHIPTREES@GMAIL.COM, SR",
    "thumb": null,
    "title": "2008 6DyK6aH3j1POwRDq4h EZnuSYCNle7JcI cargo bike (front storage)",
    "url": "https://bikeindex.org/bikes/1649500",
    "year": 2008
  },
  {
    "date_stolen": 1693281927,
    "description": null,
    "frame_colors": [
      "Purple",
      "Stickers tape or other cover-up",
      "Green"
    ],
    "frame_model": "xBy0TcOflEc1O",
    "id": 1649462,
    "is_stock_img": false,
    "large_img": null,
    "location_found": null,
    "manufacturer_name": "yrEYffBAtQ8JOk",
    "external_id": null,
    "registry_name": null,
    "registry_url": null,
    "serial": "wp7NlGSonp9MVuA",
    "status": "stolen",
    "stolen": true,
    "stolen_coordinates": [
      32.32,
      -86.9
    ],
    "stolen_location": "5 T Li Gglyl6d Ft Ks, AL LPAN@PAG.COM, AL",
    "thumb": null,
    "title": "1975 yrEYffBAtQ8JOk xBy0TcOflEc1O trail behind (half bike)",
    "url": "https://bikeindex.org/bikes/1649462",
    "year": 1975
  },
  {
    "date_stolen": 1693280021,
    "description": null,
    "frame_colors": [
      "White",
      "Pink",
      "Green"
    ],
    "frame_model": "eUu7Xkpm6M",
    "id": 1649444,
    "is_stock_img": false,
    "large_img": null,
    "location_found": null,
    "manufacturer_name": "vjrbRyufqF0o6k",
    "external_id": null,
    "registry_name": null,
    "registry_url": null,
    "serial": "mepYzGjky6RD",
    "status": "stolen",
    "stolen": true,
    "stolen_coordinates": null,
    "stolen_location": "V Hq9m J7 Bul B Pw1w, KATYCATS@HOTMAIL.COM, RS",
    "thumb": null,
    "title": "1951 vjrbRyufqF0o6k eUu7Xkpm6M e-skateboard (e-unicycle, personal mobility device, etc)",
    "url": "https://bikeindex.org/bikes/1649444",
    "year": 1951
  },
  {
    "date_stolen": 1693279680,
    "description": "It's new I never used it I have name under the frame near to the set bike made in vietnam",
    "frame_colors": [
      "Teal"
    ],
    "frame_model": "yeti sb130 lr",
    "id": 1494041,
    "is_stock_img": false,
    "large_img": null,
    "location_found": null,
    "manufacturer_name": "Yeti",
    "external_id": null,
    "registry_name": null,
    "registry_url": null,
    "serial": "0HAfd610038",
    "status": "stolen",
    "stolen": true,
    "stolen_coordinates": null,
    "stolen_location": "CA",
    "thumb": null,
    "title": "2021 Yeti yeti sb130 lr",
    "url": "https://bikeindex.org/bikes/1494041",
    "year": 2021
  },
  {
    "date_stolen": 1693279255,
    "description": null,
    "frame_colors": [
      "Stickers tape or other cover-up",
      "Silver, gray or bare metal",
      "Yellow or Gold"
    ],
    "frame_model": "zlF4cGT4vxZSf5T",
    "id": 1649441,
    "is_stock_img": false,
    "large_img": null,
    "location_found": null,
    "manufacturer_name": "Y2o6cUJjmWPAEBecXP7",
    "external_id": null,
    "registry_name": null,
    "registry_url": null,
    "serial": "V64E9c4DxIqNEE",
    "status": "stolen",
    "stolen": true,
    "stolen_coordinates": null,
    "stolen_location": "E0hl Wjq Tmxkz, CHRISTY@COASTALTANKTESTING.COM, RE",
    "thumb": null,
    "title": "1991 Y2o6cUJjmWPAEBecXP7 zlF4cGT4vxZSf5T wheelchair",
    "url": "https://bikeindex.org/bikes/1649441",
    "year": 1991
  },
  {
    "date_stolen": 1693279254,
    "description": null,
    "frame_colors": [
      "Stickers tape or other cover-up",
      "Silver, gray or bare metal",
      "Yellow or Gold"
    ],
    "frame_model": "zlF4cGT4vxZSf5T",
    "id": 1649440,
    "is_stock_img": false,
    "large_img": null,
    "location_found": null,
    "manufacturer_name": "Y2o6cUJjmWPAEBecXP7",
    "external_id": null,
    "registry_name": null,
    "registry_url": null,
    "serial": "V64E9c4DxIqNEE",
    "status": "stolen",
    "stolen": true,
    "stolen_coordinates": null,
    "stolen_location": "E0hl Wjq Tmxkz, CHRISTY@COASTALTANKTESTING.COM, RE",
    "thumb": null,
    "title": "1991 Y2o6cUJjmWPAEBecXP7 zlF4cGT4vxZSf5T wheelchair",
    "url": "https://bikeindex.org/bikes/1649440",
    "year": 1991
  },
  {
    "date_stolen": 1693279155,
    "description": null,
    "frame_colors": [
      "Black",
      "Pink",
      "Black"
    ],
    "frame_model": "3DEeLR4AWe7kzqZUK",
    "id": 1649439,
    "is_stock_img": false,
    "large_img": null,
    "location_found": null,
    "manufacturer_name": "YdRsW4uLkWrF2CW6Ar7",
    "external_id": null,
    "registry_name": null,
    "registry_url": null,
    "serial": "5Y1f08aXPxg9XAnspt6",
    "status": "stolen",
    "stolen": true,
    "stolen_coordinates": null,
    "stolen_location": "Y I8 N1g6c O62d Ar9, AJSWEIDAN@GMAIL.COM, TC",
    "thumb": null,
    "title": "1982 YdRsW4uLkWrF2CW6Ar7 3DEeLR4AWe7kzqZUK pedi cab (rickshaw)",
    "url": "https://bikeindex.org/bikes/1649439",
    "year": 1982
  },
  {
    "date_stolen": 1693278774,
    "description": null,
    "frame_colors": [
      "Green",
      "Orange"
    ],
    "frame_model": "03FXtEZ8atmyE",
    "id": 1649436,
    "is_stock_img": false,
    "large_img": null,
    "location_found": null,
    "manufacturer_name": "BZsudHkcmwkVQPt1TN",
    "external_id": null,
    "registry_name": null,
    "registry_url": null,
    "serial": "g8JH6x4UuFXJNl2GleB",
    "status": "stolen",
    "stolen": true,
    "stolen_coordinates": null,
    "stolen_location": "H0 G52bc I0oxozixxl, LPAN@PAG.COM, JM",
    "thumb": null,
    "title": "1971 BZsudHkcmwkVQPt1TN 03FXtEZ8atmyE",
    "url": "https://bikeindex.org/bikes/1649436",
    "year": 1971
  },
  {
    "date_stolen": 1693278000,
    "description": null,
    "frame_colors": [
      "Black"
    ],
    "frame_model": "Bronson",
    "id": 1649448,
    "is_stock_img": false,
    "large_img": null,
    "location_found": null,
    "manufacturer_name": "Santa Cruz",
    "external_id": null,
    "registry_name": null,
    "registry_url": null,
    "serial": "PS1804P-13021MC",
    "status": "stolen",
    "stolen": true,
    "stolen_coordinates": [
      38.89,
      -120
    ],
    "stolen_location": "Lake Tahoe, CA 96150, US",
    "thumb": null,
    "title": "2017 Santa Cruz Bronson",
    "url": "https://bikeindex.org/bikes/1649448",
    "year": 2017
  },
  {
    "date_stolen": 1693278000,
    "description": "7 Gears, 2 Battery Packs, 500 W motor 2 mirrors Tan Wide seat",
    "frame_colors": [
      "Red"
    ],
    "frame_model": "Model C",
    "id": 1649443,
    "is_stock_img": false,
    "large_img": "https://files.bikeindex.org/uploads/Pu/740825/large_1618006283717_resized.jpg",
    "location_found": null,
    "manufacturer_name": "Electric Bike Company",
    "external_id": null,
    "registry_name": null,
    "registry_url": null,
    "serial": "Unknown",
    "status": "stolen",
    "stolen": true,
    "stolen_coordinates": [
      40.21,
      -111.63
    ],
    "stolen_location": "Provo, UT 84606, US",
    "thumb": "https://files.bikeindex.org/uploads/Pu/740825/small_1618006283717_resized.jpg",
    "title": "2023 Electric Bike Company Model C",
    "url": "https://bikeindex.org/bikes/1649443",
    "year": 2023
  },
  {
    "date_stolen": 1693276298,
    "description": null,
    "frame_colors": [
      "Red",
      "Teal",
      "Yellow or Gold"
    ],
    "frame_model": "RYZqgsLc1x0TTXO5J8uT",
    "id": 1649421,
    "is_stock_img": false,
    "large_img": null,
    "location_found": null,
    "manufacturer_name": "7o8uJ8oXOvY6",
    "external_id": null,
    "registry_name": null,
    "registry_url": null,
    "serial": "4dcZ3HUUR7RPoSZozWj",
    "status": "stolen",
    "stolen": true,
    "stolen_coordinates": null,
    "stolen_location": "Z D Fli10 Pin F Ih3 Nx, LPAN@PAG.COM, ST",
    "thumb": null,
    "title": "1965 7o8uJ8oXOvY6 RYZqgsLc1x0TTXO5J8uT e-skateboard (e-unicycle, personal mobility device, etc)",
    "url": "https://bikeindex.org/bikes/1649421",
    "year": 1965
  },
  {
    "date_stolen": 1693276014,
    "description": null,
    "frame_colors": [
      "Green"
    ],
    "frame_model": "Major T",
    "id": 1649419,
    "is_stock_img": false,
    "large_img": null,
    "location_found": null,
    "manufacturer_name": "Fatback",
    "external_id": null,
    "registry_name": null,
    "registry_url": null,
    "serial": "SBW20080461",
    "status": "stolen",
    "stolen": true,
    "stolen_coordinates": [
      39.7,
      -105.04
    ],
    "stolen_location": "Denver, CO 80219, US",
    "thumb": null,
    "title": "2023 Fatback Major T cargo bike (rear storage)",
    "url": "https://bikeindex.org/bikes/1649419",
    "year": 2023
  },
  {
    "date_stolen": 1693275059,
    "description": null,
    "frame_colors": [
      "Blue",
      "Teal",
      "Silver, gray or bare metal"
    ],
    "frame_model": "5PRHEQBuPJiN3",
    "id": 1649407,
    "is_stock_img": false,
    "large_img": null,
    "location_found": null,
    "manufacturer_name": "uMAmcDLNVBl9",
    "external_id": null,
    "registry_name": null,
    "registry_url": null,
    "serial": "DUMEpjtJc8BONySb",
    "status": "stolen",
    "stolen": true,
    "stolen_coordinates": null,
    "stolen_location": "Y R Otpu Ujn Po H Lx, BIB1991@AOL.COM, EE",
    "thumb": null,
    "title": "2016 uMAmcDLNVBl9 5PRHEQBuPJiN3 cargo tricycle (rear storage)",
    "url": "https://bikeindex.org/bikes/1649407",
    "year": 2016
  },
  {
    "date_stolen": 1693274825,
    "description": null,
    "frame_colors": [
      "Orange"
    ],
    "frame_model": "Timberjack",
    "id": 1649410,
    "is_stock_img": false,
    "large_img": null,
    "location_found": null,
    "manufacturer_name": "Salsa",
    "external_id": null,
    "registry_name": null,
    "registry_url": null,
    "serial": "Unknown",
    "status": "stolen",
    "stolen": true,
    "stolen_coordinates": [
      40.02,
      -105.27
    ],
    "stolen_location": "Boulder, CO 80310, US",
    "thumb": null,
    "title": "2018 Salsa Timberjack",
    "url": "https://bikeindex.org/bikes/1649410",
    "year": 2018
  },
  {
    "date_stolen": 1693273775,
    "description": null,
    "frame_colors": [
      "Blue",
      "Red",
      "Yellow or Gold"
    ],
    "frame_model": "aLra600GlkiYHfcv5mI",
    "id": 1649391,
    "is_stock_img": false,
    "large_img": null,
    "location_found": null,
    "manufacturer_name": "qzLyNxEJqFHt0qM",
    "external_id": null,
    "registry_name": null,
    "registry_url": null,
    "serial": "lWt8qIb86ukoxoaPl9DH",
    "status": "stolen",
    "stolen": true,
    "stolen_coordinates": null,
    "stolen_location": "4 Ku Si Dw Kt Fp Ahp, BRIGGSWJ1986@GMAIL.COM, KM",
    "thumb": null,
    "title": "1989 qzLyNxEJqFHt0qM aLra600GlkiYHfcv5mI wheelchair",
    "url": "https://bikeindex.org/bikes/1649391",
    "year": 1989
  },
  {
    "date_stolen": 1693273443,
    "description": "Modified with a Sturmey Archer rear hub and a green front crank.",
    "frame_colors": [
      "Blue"
    ],
    "frame_model": "Sportif",
    "id": 1649387,
    "is_stock_img": false,
    "large_img": "https://files.bikeindex.org/uploads/Pu/740782/large_IMG_0074.jpeg",
    "location_found": null,
    "manufacturer_name": "Raleigh",
    "external_id": null,
    "registry_name": null,
    "registry_url": null,
    "serial": "Unknown",
    "status": "stolen",
    "stolen": true,
    "stolen_coordinates": [
      37.77,
      -122.44
    ],
    "stolen_location": "San Francisco, CA 94117, US",
    "thumb": "https://files.bikeindex.org/uploads/Pu/740782/small_IMG_0074.jpeg",
    "title": "1985 Raleigh Sportif",
    "url": "https://bikeindex.org/bikes/1649387",
    "year": 1985
  },
  {
    "date_stolen": 1693273105,
    "description": null,
    "frame_colors": [
      "Teal",
      "Red",
      "Brown"
    ],
    "frame_model": "DQdV3mm16ghGYwW",
    "id": 1649382,
    "is_stock_img": false,
    "large_img": null,
    "location_found": null,
    "manufacturer_name": "or0kfIP25sP5OI9gR",
    "external_id": null,
    "registry_name": null,
    "registry_url": null,
    "serial": "dZZfsHiA4FNy02",
    "status": "stolen",
    "stolen": true,
    "stolen_coordinates": null,
    "stolen_location": "Grx Yz G6 Wjrs, THOMASHIGGINSON5@GMAIL.COM, NE",
    "thumb": null,
    "title": "1971 or0kfIP25sP5OI9gR DQdV3mm16ghGYwW cargo tricycle (front storage)",
    "url": "https://bikeindex.org/bikes/1649382",
    "year": 1971
  },
  {
    "date_stolen": 1693271941,
    "description": null,
    "frame_colors": [
      "Silver, gray or bare metal",
      "Purple",
      "Stickers tape or other cover-up"
    ],
    "frame_model": "viNrgVEYJLB",
    "id": 1649374,
    "is_stock_img": false,
    "large_img": null,
    "location_found": null,
    "manufacturer_name": "dKZJSNN94mbV4Y",
    "external_id": null,
    "registry_name": null,
    "registry_url": null,
    "serial": "hi6OYWekwzpo",
    "status": "stolen",
    "stolen": true,
    "stolen_coordinates": null,
    "stolen_location": "Garz Vo9nb Khkxv Cv Dk, MEGRYAN6706@GMAIL.COM, IE",
    "thumb": null,
    "title": "1935 dKZJSNN94mbV4Y viNrgVEYJLB penny farthing",
    "url": "https://bikeindex.org/bikes/1649374",
    "year": 1935
  },
  {
    "date_stolen": 1693271939,
    "description": null,
    "frame_colors": [
      "Silver, gray or bare metal",
      "Purple",
      "Stickers tape or other cover-up"
    ],
    "frame_model": "viNrgVEYJLB",
    "id": 1649373,
    "is_stock_img": false,
    "large_img": null,
    "location_found": null,
    "manufacturer_name": "dKZJSNN94mbV4Y",
    "external_id": null,
    "registry_name": null,
    "registry_url": null,
    "serial": "hi6OYWekwzpo",
    "status": "stolen",
    "stolen": true,
    "stolen_coordinates": null,
    "stolen_location": "Garz Vo9nb Khkxv Cv Dk, MEGRYAN6706@GMAIL.COM, IE",
    "thumb": null,
    "title": "1935 dKZJSNN94mbV4Y viNrgVEYJLB penny farthing",
    "url": "https://bikeindex.org/bikes/1649373",
    "year": 1935
  },
  {
    "date_stolen": 1693269631,
    "description": null,
    "frame_colors": [
      "Brown",
      "Yellow or Gold",
      "Teal"
    ],
    "frame_model": "I1btDDvJns3",
    "id": 1649350,
    "is_stock_img": false,
    "large_img": null,
    "location_found": null,
    "manufacturer_name": "iXZ9OgMPM4Q7Ce",
    "external_id": null,
    "registry_name": null,
    "registry_url": null,
    "serial": "OYvGBhaYg0XI9JUQVljn",
    "status": "stolen",
    "stolen": true,
    "stolen_coordinates": null,
    "stolen_location": "Ix X Ywx J Sse Bo Ukc Xg, LPAN@PAG.COM, MG",
    "thumb": null,
    "title": "2009 iXZ9OgMPM4Q7Ce I1btDDvJns3 stroller",
    "url": "https://bikeindex.org/bikes/1649350",
    "year": 2009
  },
  {
    "date_stolen": 1693269608,
    "description": null,
    "frame_colors": [
      "Brown",
      "Yellow or Gold",
      "Teal"
    ],
    "frame_model": "I1btDDvJns3",
    "id": 1649349,
    "is_stock_img": false,
    "large_img": null,
    "location_found": null,
    "manufacturer_name": "iXZ9OgMPM4Q7Ce",
    "external_id": null,
    "registry_name": null,
    "registry_url": null,
    "serial": "OYvGBhaYg0XI9JUQVljn",
    "status": "stolen",
    "stolen": true,
    "stolen_coordinates": null,
    "stolen_location": "Ix X Ywx J Sse Bo Ukc Xg, LPAN@PAG.COM, MG",
    "thumb": null,
    "title": "2009 iXZ9OgMPM4Q7Ce I1btDDvJns3 stroller",
    "url": "https://bikeindex.org/bikes/1649349",
    "year": 2009
  },
  {
    "date_stolen": 1693269056,
    "description": null,
    "frame_colors": [
      "Stickers tape or other cover-up",
      "Purple",
      "Green"
    ],
    "frame_model": "IOrmf1HjUocElSX28c",
    "id": 1649345,
    "is_stock_img": false,
    "large_img": null,
    "location_found": null,
    "manufacturer_name": "S6GITzM0qV7Z5r",
    "external_id": null,
    "registry_name": null,
    "registry_url": null,
    "serial": "ffcSZscx8D",
    "status": "stolen",
    "stolen": true,
    "stolen_coordinates": null,
    "stolen_location": "Qopm Ds R Ov I Bf M8 Xv, RICK.ELLIOTT@YAHOO.COM, AG",
    "thumb": null,
    "title": "1968 S6GITzM0qV7Z5r IOrmf1HjUocElSX28c",
    "url": "https://bikeindex.org/bikes/1649345",
    "year": 1968
  },
  {
    "date_stolen": 1693268900,
    "description": null,
    "frame_colors": [
      "Black"
    ],
    "frame_model": "XP 2.0",
    "id": 1649354,
    "is_stock_img": false,
    "large_img": "https://files.bikeindex.org/uploads/Pu/740767/large_IMG_5724.jpeg",
    "location_found": null,
    "manufacturer_name": "Lectric eBikes",
    "external_id": null,
    "registry_name": null,
    "registry_url": null,
    "serial": "GX2021985126",
    "status": "stolen",
    "stolen": true,
    "stolen_coordinates": [
      32.94,
      -117.21
    ],
    "stolen_location": "Fullerton, CA 92130, US",
    "thumb": "https://files.bikeindex.org/uploads/Pu/740767/small_IMG_5724.jpeg",
    "title": "Lectric eBikes XP 2.0",
    "url": "https://bikeindex.org/bikes/1649354",
    "year": null
  },
  {
    "date_stolen": 1693267200,
    "description": null,
    "frame_colors": [
      "Brown"
    ],
    "frame_model": null,
    "id": 1129889,
    "is_stock_img": false,
    "large_img": null,
    "location_found": null,
    "manufacturer_name": "bayside",
    "external_id": null,
    "registry_name": null,
    "registry_url": null,
    "serial": "G2006125873",
    "status": "stolen",
    "stolen": true,
    "stolen_coordinates": [
      40.01,
      -105.27
    ],
    "stolen_location": "Boulder, CO 80302, US",
    "thumb": null,
    "title": "2021 bayside",
    "url": "https://bikeindex.org/bikes/1129889",
    "year": 2021
  },
  {
    "date_stolen": 1693267200,
    "description": "MY BIKE HAVE LOOK NEW. PLEASE FIND MY BIKE :(",
    "frame_colors": [
      "Green"
    ],
    "frame_model": "SCOTT 2021 CONTESSA ACTIVE 50 TEAL GREEM XSSMALL 27.5",
    "id": 1649572,
    "is_stock_img": false,
    "large_img": null,
    "location_found": null,
    "manufacturer_name": "SCOTT",
    "external_id": null,
    "registry_name": null,
    "registry_url": null,
    "serial": "AS10227553",
    "status": "stolen",
    "stolen": true,
    "stolen_coordinates": [
      53.52,
      -113.49
    ],
    "stolen_location": "Edmonton, T6E 3T7, CA",
    "thumb": null,
    "title": "2021 SCOTT SCOTT 2021 CONTESSA ACTIVE 50 TEAL GR...",
    "url": "https://bikeindex.org/bikes/1649572",
    "year": 2021
  },
  {
    "date_stolen": 1693266735,
    "description": null,
    "frame_colors": [
      "Yellow or Gold",
      "Blue",
      "Pink"
    ],
    "frame_model": "paToxnThnGR6",
    "id": 1649329,
    "is_stock_img": false,
    "large_img": null,
    "location_found": null,
    "manufacturer_name": "mhYAo9cPygK91Lg9Uh",
    "external_id": null,
    "registry_name": null,
    "registry_url": null,
    "serial": "CiRCjTVfKzIok12",
    "status": "stolen",
    "stolen": true,
    "stolen_coordinates": null,
    "stolen_location": "Mmz Vh K Eq Fp, LPAN@PAG.COM, SL",
    "thumb": null,
    "title": "1909 mhYAo9cPygK91Lg9Uh paToxnThnGR6 pedi cab (rickshaw)",
    "url": "https://bikeindex.org/bikes/1649329",
    "year": 1909
  },
  {
    "date_stolen": 1693264145,
    "description": null,
    "frame_colors": [
      "White",
      "Green",
      "Stickers tape or other cover-up"
    ],
    "frame_model": "4BNUDBXVWzJpmYE75I",
    "id": 1649300,
    "is_stock_img": false,
    "large_img": null,
    "location_found": null,
    "manufacturer_name": "rmnff1bfUpAxOlhz",
    "external_id": null,
    "registry_name": null,
    "registry_url": null,
    "serial": "9MpqKguYAr2mmO4p9Z",
    "status": "stolen",
    "stolen": true,
    "stolen_coordinates": null,
    "stolen_location": "77f Mg Spk Ajfo2 H Vl, BRENDA6M@HOTMAIL.COM, GY",
    "thumb": null,
    "title": "1916 rmnff1bfUpAxOlhz 4BNUDBXVWzJpmYE75I",
    "url": "https://bikeindex.org/bikes/1649300",
    "year": 1916
  },
  {
    "date_stolen": 1693263613,
    "description": null,
    "frame_colors": [
      "Teal",
      "Brown",
      "Brown"
    ],
    "frame_model": "Zuwi7jL2kh3NGR6u8h",
    "id": 1649296,
    "is_stock_img": false,
    "large_img": null,
    "location_found": null,
    "manufacturer_name": "bOFQWXJlnbG",
    "external_id": null,
    "registry_name": null,
    "registry_url": null,
    "serial": "LnlY9GZfsW82fYlg6CHB",
    "status": "stolen",
    "stolen": true,
    "stolen_coordinates": null,
    "stolen_location": "9a40p C Yb9 Hu64 Mk Rwf, SHARK28@WP.PL, SA",
    "thumb": null,
    "title": "2019 bOFQWXJlnbG Zuwi7jL2kh3NGR6u8h wheelchair",
    "url": "https://bikeindex.org/bikes/1649296",
    "year": 2019
  },
  {
    "date_stolen": 1693263611,
    "description": null,
    "frame_colors": [
      "Teal",
      "Brown",
      "Brown"
    ],
    "frame_model": "Zuwi7jL2kh3NGR6u8h",
    "id": 1649295,
    "is_stock_img": false,
    "large_img": null,
    "location_found": null,
    "manufacturer_name": "bOFQWXJlnbG",
    "external_id": null,
    "registry_name": null,
    "registry_url": null,
    "serial": "LnlY9GZfsW82fYlg6CHB",
    "status": "stolen",
    "stolen": true,
    "stolen_coordinates": null,
    "stolen_location": "9a40p C Yb9 Hu64 Mk Rwf, SHARK28@WP.PL, SA",
    "thumb": null,
    "title": "2019 bOFQWXJlnbG Zuwi7jL2kh3NGR6u8h wheelchair",
    "url": "https://bikeindex.org/bikes/1649295",
    "year": 2019
  },
  {
    "date_stolen": 1693263600,
    "description": null,
    "frame_colors": [
      "Silver, gray or bare metal"
    ],
    "frame_model": "Radrunner Plus",
    "id": 1279333,
    "is_stock_img": false,
    "large_img": "https://files.bikeindex.org/uploads/Pu/561045/large_PXL_20220428_165926522.jpg",
    "location_found": null,
    "manufacturer_name": "Rad Power Bikes",
    "external_id": null,
    "registry_name": null,
    "registry_url": null,
    "serial": "VP1B22V0105",
    "status": "stolen",
    "stolen": true,
    "stolen_coordinates": [
      47.68,
      -122.3
    ],
    "stolen_location": "Seattle, WA 98115, US",
    "thumb": "https://files.bikeindex.org/uploads/Pu/561045/small_PXL_20220428_165926522.jpg",
    "title": "2022 Rad Power Bikes Radrunner Plus",
    "url": "https://bikeindex.org/bikes/1279333",
    "year": 2022
  },
  {
    "date_stolen": 1693263600,
    "description": "",
    "frame_colors": [
      "Black"
    ],
    "frame_model": "FastRoad E+ EX Pro",
    "id": 1649310,
    "is_stock_img": false,
    "large_img": null,
    "location_found": null,
    "manufacturer_name": "Giant",
    "external_id": null,
    "registry_name": null,
    "registry_url": null,
    "serial": "G9EA24754",
    "status": "stolen",
    "stolen": true,
    "stolen_coordinates": [
      51.02,
      -114.11
    ],
    "stolen_location": "Calgary, T2T 6B4, CA",
    "thumb": null,
    "title": "Giant FastRoad E+ EX Pro",
    "url": "https://bikeindex.org/bikes/1649310",
    "year": null
  },
  {
    "date_stolen": 1693263600,
    "description": "Cream-colored commuter bike with front and rear fenders and rack.",
    "frame_colors": [
      "White"
    ],
    "frame_model": "",
    "id": 394505,
    "is_stock_img": false,
    "large_img": "https://files.bikeindex.org/uploads/Pu/119232/large_94FE52BC-FC9E-489C-B8B8-34F9868E29C2.jpeg",
    "location_found": null,
    "manufacturer_name": "Trek",
    "external_id": null,
    "registry_name": null,
    "registry_url": null,
    "serial": "WTU199SI3436C",
    "status": "stolen",
    "stolen": true,
    "stolen_coordinates": [
      47.63,
      -122.29
    ],
    "stolen_location": "Seattle, WA 98112, US",
    "thumb": "https://files.bikeindex.org/uploads/Pu/119232/small_94FE52BC-FC9E-489C-B8B8-34F9868E29C2.jpeg",
    "title": "Trek",
    "url": "https://bikeindex.org/bikes/394505",
    "year": null
  },
  {
    "date_stolen": 1693262742,
    "description": null,
    "frame_colors": [
      "Black",
      "Brown",
      "Yellow or Gold"
    ],
    "frame_model": "tnB4xR7HyFKpp6qtt0e",
    "id": 1649287,
    "is_stock_img": false,
    "large_img": null,
    "location_found": null,
    "manufacturer_name": "gemLN7WP6Y",
    "external_id": null,
    "registry_name": null,
    "registry_url": null,
    "serial": "YJMxPircAF",
    "status": "stolen",
    "stolen": true,
    "stolen_coordinates": null,
    "stolen_location": "It Lxtlx X53, KJLOMAX0@GMAIL.COM, KM",
    "thumb": null,
    "title": "1958 gemLN7WP6Y tnB4xR7HyFKpp6qtt0e",
    "url": "https://bikeindex.org/bikes/1649287",
    "year": 1958
  },
  {
    "date_stolen": 1693260678,
    "description": null,
    "frame_colors": [
      "Silver, gray or bare metal",
      "Yellow or Gold",
      "Silver, gray or bare metal"
    ],
    "frame_model": "vrPL2K9b9wp",
    "id": 1649268,
    "is_stock_img": false,
    "large_img": null,
    "location_found": null,
    "manufacturer_name": "ZoIlKseya7E2UYIjdwp",
    "external_id": null,
    "registry_name": null,
    "registry_url": null,
    "serial": "t6LOmwgs1lvwc",
    "status": "stolen",
    "stolen": true,
    "stolen_coordinates": null,
    "stolen_location": "Ts Fi To Oc Q Wh6uo, LPAN@PAG.COM, PN",
    "thumb": null,
    "title": "2016 ZoIlKseya7E2UYIjdwp vrPL2K9b9wp pedi cab (rickshaw)",
    "url": "https://bikeindex.org/bikes/1649268",
    "year": 2016
  },
  {
    "date_stolen": 1693260006,
    "description": null,
    "frame_colors": [
      "Black"
    ],
    "frame_model": "Marlin 7",
    "id": 1649266,
    "is_stock_img": false,
    "large_img": "https://files.bikeindex.org/uploads/Pu/740708/large_IMG_5137.png",
    "location_found": null,
    "manufacturer_name": "Trek",
    "external_id": null,
    "registry_name": null,
    "registry_url": null,
    "serial": "Unknown",
    "status": "stolen",
    "stolen": true,
    "stolen_coordinates": [
      38.86,
      -104.87
    ],
    "stolen_location": "Colorado Springs, CO 80904, US",
    "thumb": "https://files.bikeindex.org/uploads/Pu/740708/small_IMG_5137.png",
    "title": "2023 Trek Marlin 7",
    "url": "https://bikeindex.org/bikes/1649266",
    "year": 2023
  },
  {
    "date_stolen": 1693260000,
    "description": "Very distinctive bright volt green. Has a vertical water bottle holder. Largest gear on the cassette has a tooth missing",
    "frame_colors": [
      "Green"
    ],
    "frame_model": "Roscoe 7",
    "id": 1649283,
    "is_stock_img": false,
    "large_img": "https://files.bikeindex.org/uploads/Pu/740715/large_IMG_20190707_185613.jpg",
    "location_found": null,
    "manufacturer_name": "Trek",
    "external_id": null,
    "registry_name": null,
    "registry_url": null,
    "serial": "WTU248C3415N",
    "status": "stolen",
    "stolen": true,
    "stolen_coordinates": [
      51.04,
      -114.09
    ],
    "stolen_location": "Calgary, T3C 0M5, CA",
    "thumb": "https://files.bikeindex.org/uploads/Pu/740715/small_IMG_20190707_185613.jpg",
    "title": "2019 Trek Roscoe 7",
    "url": "https://bikeindex.org/bikes/1649283",
    "year": 2019
  },
  {
    "date_stolen": 1693259764,
    "description": null,
    "frame_colors": [
      "Green",
      "Blue",
      "Yellow or Gold"
    ],
    "frame_model": "ynElnNyoJr4ew",
    "id": 1649264,
    "is_stock_img": false,
    "large_img": null,
    "location_found": null,
    "manufacturer_name": "4ngNJVVDKJitHYFx",
    "external_id": null,
    "registry_name": null,
    "registry_url": null,
    "serial": "oiGAqKF367ReUYMN4iJ",
    "status": "stolen",
    "stolen": true,
    "stolen_coordinates": null,
    "stolen_location": "H Re9 Aqoold Xl1b265q, LPAN@PAG.COM, CU",
    "thumb": null,
    "title": "2013 4ngNJVVDKJitHYFx ynElnNyoJr4ew stroller",
    "url": "https://bikeindex.org/bikes/1649264",
    "year": 2013
  },
  {
    "date_stolen": 1693259553,
    "description": null,
    "frame_colors": [
      "Purple",
      "Blue"
    ],
    "frame_model": "oxHHpSq6XxvSONvnE9",
    "id": 1649261,
    "is_stock_img": false,
    "large_img": null,
    "location_found": null,
    "manufacturer_name": "fkyUeouPQjtQUk7myRGc",
    "external_id": null,
    "registry_name": null,
    "registry_url": null,
    "serial": "KZDEV1gB1S4NGB0SM2z",
    "status": "stolen",
    "stolen": true,
    "stolen_coordinates": null,
    "stolen_location": "Uimw5 Uh Es, BECKYFANG@ROCKETMAIL.COM, AI",
    "thumb": null,
    "title": "1961 fkyUeouPQjtQUk7myRGc oxHHpSq6XxvSONvnE9 cargo tricycle (front storage)",
    "url": "https://bikeindex.org/bikes/1649261",
    "year": 1961
  },
  {
    "date_stolen": 1693259551,
    "description": null,
    "frame_colors": [
      "Purple",
      "Blue"
    ],
    "frame_model": "oxHHpSq6XxvSONvnE9",
    "id": 1649260,
    "is_stock_img": false,
    "large_img": null,
    "location_found": null,
    "manufacturer_name": "fkyUeouPQjtQUk7myRGc",
    "external_id": null,
    "registry_name": null,
    "registry_url": null,
    "serial": "KZDEV1gB1S4NGB0SM2z",
    "status": "stolen",
    "stolen": true,
    "stolen_coordinates": null,
    "stolen_location": "Uimw5 Uh Es, BECKYFANG@ROCKETMAIL.COM, AI",
    "thumb": null,
    "title": "1961 fkyUeouPQjtQUk7myRGc oxHHpSq6XxvSONvnE9 cargo tricycle (front storage)",
    "url": "https://bikeindex.org/bikes/1649260",
    "year": 1961
  },
  {
    "date_stolen": 1693259400,
    "description": null,
    "frame_colors": [
      "Brown"
    ],
    "frame_model": "Aventure1",
    "id": 1649379,
    "is_stock_img": false,
    "large_img": "https://files.bikeindex.org/uploads/Pu/740779/large_IMG_20230515_154412861.jpg",
    "location_found": null,
    "manufacturer_name": "Aventón",
    "external_id": null,
    "registry_name": null,
    "registry_url": null,
    "serial": "JH21F2708",
    "status": "stolen",
    "stolen": true,
    "stolen_coordinates": [
      44.04,
      -123.23
    ],
    "stolen_location": "Eugene, OR 97402, US",
    "thumb": "https://files.bikeindex.org/uploads/Pu/740779/small_IMG_20230515_154412861.jpg",
    "title": "2022 Aventón Aventure1",
    "url": "https://bikeindex.org/bikes/1649379",
    "year": 2022
  },
  {
    "date_stolen": 1693258697,
    "description": null,
    "frame_colors": [
      "Black"
    ],
    "frame_model": "Storm",
    "id": 1649251,
    "is_stock_img": false,
    "large_img": null,
    "location_found": null,
    "manufacturer_name": "Norco Bikes",
    "external_id": null,
    "registry_name": null,
    "registry_url": null,
    "serial": "Unknown",
    "status": "stolen",
    "stolen": true,
    "stolen_coordinates": [
      53.54,
      -113.44
    ],
    "stolen_location": "Edmonton, T6A 0A8, CA",
    "thumb": null,
    "title": "Norco Bikes Storm",
    "url": "https://bikeindex.org/bikes/1649251",
    "year": null
  },
  {
    "date_stolen": 1693257401,
    "description": null,
    "frame_colors": [
      "Silver, gray or bare metal"
    ],
    "frame_model": "Lanai",
    "id": 1649236,
    "is_stock_img": false,
    "large_img": null,
    "location_found": null,
    "manufacturer_name": "Kona",
    "external_id": null,
    "registry_name": null,
    "registry_url": null,
    "serial": "in20092448",
    "status": "stolen",
    "stolen": true,
    "stolen_coordinates": [
      53.56,
      -113.25
    ],
    "stolen_location": "Sherwood Park, T8H 0Y4, CA",
    "thumb": null,
    "title": "2021 Kona Lanai",
    "url": "https://bikeindex.org/bikes/1649236",
    "year": 2021
  },
  {
    "date_stolen": 1693257300,
    "description": null,
    "frame_colors": [
      "Black"
    ],
    "frame_model": null,
    "id": 1649450,
    "is_stock_img": false,
    "large_img": null,
    "location_found": null,
    "manufacturer_name": "Nishiki",
    "external_id": null,
    "registry_name": null,
    "registry_url": null,
    "serial": "Ec221200258",
    "status": "stolen",
    "stolen": true,
    "stolen_coordinates": [
      39.98,
      -105.25
    ],
    "stolen_location": "Boulder, CO 80305, US",
    "thumb": null,
    "title": "2023 Nishiki",
    "url": "https://bikeindex.org/bikes/1649450",
    "year": 2023
  },
  {
    "date_stolen": 1693257008,
    "description": null,
    "frame_colors": [
      "White",
      "Pink",
      "Orange"
    ],
    "frame_model": "g3O38C08LWPhuz1cRsEn",
    "id": 1649226,
    "is_stock_img": false,
    "large_img": null,
    "location_found": null,
    "manufacturer_name": "p1E3UhjTPz",
    "external_id": null,
    "registry_name": null,
    "registry_url": null,
    "serial": "idc9s1WQRLVR",
    "status": "stolen",
    "stolen": true,
    "stolen_coordinates": null,
    "stolen_location": "Lj Ib Wj Jg Ofidm C Bol, RJDECK37@GMAIL.COM, BI",
    "thumb": null,
    "title": "1923 p1E3UhjTPz g3O38C08LWPhuz1cRsEn pedi cab (rickshaw)",
    "url": "https://bikeindex.org/bikes/1649226",
    "year": 1923
  },
  {
    "date_stolen": 1693254314,
    "description": null,
    "frame_colors": [
      "Stickers tape or other cover-up",
      "Stickers tape or other cover-up",
      "Pink"
    ],
    "frame_model": "JsRT0SHgv9jL0aQGvh",
    "id": 1649195,
    "is_stock_img": false,
    "large_img": null,
    "location_found": null,
    "manufacturer_name": "5rVg28ggpp",
    "external_id": null,
    "registry_name": null,
    "registry_url": null,
    "serial": "aZx5JWwG0eSmWFErQi",
    "status": "stolen",
    "stolen": true,
    "stolen_coordinates": null,
    "stolen_location": "Chp09lj5 M Rjj, SHEILABARNIM@EXECULINK.COM, TJ",
    "thumb": null,
    "title": "2021 5rVg28ggpp JsRT0SHgv9jL0aQGvh e-skateboard (e-unicycle, personal mobility device, etc)",
    "url": "https://bikeindex.org/bikes/1649195",
    "year": 2021
  },
  {
    "date_stolen": 1693254238,
    "description": null,
    "frame_colors": [
      "Red"
    ],
    "frame_model": "Overdrive ",
    "id": 1649197,
    "is_stock_img": false,
    "large_img": "https://files.bikeindex.org/uploads/Pu/740679/large_FF37F790-EB27-48E6-A78D-A4D0361FA9B9.jpeg",
    "location_found": null,
    "manufacturer_name": "Diamondback",
    "external_id": null,
    "registry_name": null,
    "registry_url": null,
    "serial": "u141k15671",
    "status": "stolen",
    "stolen": true,
    "stolen_coordinates": [
      40.53,
      -105.14
    ],
    "stolen_location": "Fort Collins, CO 80526, US",
    "thumb": "https://files.bikeindex.org/uploads/Pu/740679/small_FF37F790-EB27-48E6-A78D-A4D0361FA9B9.jpeg",
    "title": "Diamondback Overdrive",
    "url": "https://bikeindex.org/bikes/1649197",
    "year": null
  },
  {
    "date_stolen": 1693253908,
    "description": null,
    "frame_colors": [
      "Red",
      "Stickers tape or other cover-up",
      "Blue"
    ],
    "frame_model": "WJMMZxb6sksavVTG8cM",
    "id": 1649190,
    "is_stock_img": false,
    "large_img": null,
    "location_found": null,
    "manufacturer_name": "V3JbL9mAFr",
    "external_id": null,
    "registry_name": null,
    "registry_url": null,
    "serial": "qXzLH2B3t1M",
    "status": "stolen",
    "stolen": true,
    "stolen_coordinates": null,
    "stolen_location": "E D Ygw Xas C Kcrnkks, JMARTINS1@COMCAST.NET, IE",
    "thumb": null,
    "title": "1987 V3JbL9mAFr WJMMZxb6sksavVTG8cM recumbent",
    "url": "https://bikeindex.org/bikes/1649190",
    "year": 1987
  },
  {
    "date_stolen": 1693253637,
    "description": null,
    "frame_colors": [
      "Pink",
      "Orange",
      "Green"
    ],
    "frame_model": "IIKtLCsbm09zCEQ",
    "id": 1649187,
    "is_stock_img": false,
    "large_img": null,
    "location_found": null,
    "manufacturer_name": "WL9AH0NhopdPYArrThCw",
    "external_id": null,
    "registry_name": null,
    "registry_url": null,
    "serial": "1BThVSWFeEpktb",
    "status": "stolen",
    "stolen": true,
    "stolen_coordinates": null,
    "stolen_location": "F Rc Br Ek Hw3x Qr9, RKM800VE@SHAW.CA, YE",
    "thumb": null,
    "title": "1940 WL9AH0NhopdPYArrThCw IIKtLCsbm09zCEQ e-skateboard (e-unicycle, personal mobility device, etc)",
    "url": "https://bikeindex.org/bikes/1649187",
    "year": 1940
  },
  {
    "date_stolen": 1693253635,
    "description": null,
    "frame_colors": [
      "Pink",
      "Orange",
      "Green"
    ],
    "frame_model": "IIKtLCsbm09zCEQ",
    "id": 1649186,
    "is_stock_img": false,
    "large_img": null,
    "location_found": null,
    "manufacturer_name": "WL9AH0NhopdPYArrThCw",
    "external_id": null,
    "registry_name": null,
    "registry_url": null,
    "serial": "1BThVSWFeEpktb",
    "status": "stolen",
    "stolen": true,
    "stolen_coordinates": null,
    "stolen_location": "F Rc Br Ek Hw3x Qr9, RKM800VE@SHAW.CA, YE",
    "thumb": null,
    "title": "1940 WL9AH0NhopdPYArrThCw IIKtLCsbm09zCEQ e-skateboard (e-unicycle, personal mobility device, etc)",
    "url": "https://bikeindex.org/bikes/1649186",
    "year": 1940
  },
  {
    "date_stolen": 1693253487,
    "description": null,
    "frame_colors": [
      "Orange",
      "Brown",
      "Red"
    ],
    "frame_model": "q67OMebGnhiPRwzf",
    "id": 1649183,
    "is_stock_img": false,
    "large_img": null,
    "location_found": null,
    "manufacturer_name": "KCXPLlA1P86lE9YqmpK",
    "external_id": null,
    "registry_name": null,
    "registry_url": null,
    "serial": "9WlR1zCFFsakwb3LY",
    "status": "stolen",
    "stolen": true,
    "stolen_coordinates": null,
    "stolen_location": "E Xfyak G Vaj, LPAN@PAG.COM, GP",
    "thumb": null,
    "title": "1928 KCXPLlA1P86lE9YqmpK q67OMebGnhiPRwzf recumbent",
    "url": "https://bikeindex.org/bikes/1649183",
    "year": 1928
  },
  {
    "date_stolen": 1693253340,
    "description": null,
    "frame_colors": [
      "Yellow or Gold",
      "Teal",
      "Yellow or Gold"
    ],
    "frame_model": "rmYLcFEYHbChX",
    "id": 1649176,
    "is_stock_img": false,
    "large_img": null,
    "location_found": null,
    "manufacturer_name": "X4PpSzOmvXjW",
    "external_id": null,
    "registry_name": null,
    "registry_url": null,
    "serial": "eg0qiyn18al23mpSujd",
    "status": "stolen",
    "stolen": true,
    "stolen_coordinates": null,
    "stolen_location": "S0 Fp Rx Li Gjf6t, RKM800VE@SHAW.CA, ZW",
    "thumb": null,
    "title": "2016 X4PpSzOmvXjW rmYLcFEYHbChX e-skateboard (e-unicycle, personal mobility device, etc)",
    "url": "https://bikeindex.org/bikes/1649176",
    "year": 2016
  },
  {
    "date_stolen": 1693253059,
    "description": null,
    "frame_colors": [
      "Stickers tape or other cover-up",
      "Purple",
      "Silver, gray or bare metal"
    ],
    "frame_model": "GRDpA5otxkSuQ9PrDT",
    "id": 1649169,
    "is_stock_img": false,
    "large_img": null,
    "location_found": null,
    "manufacturer_name": "zpoz6o2JZI38p",
    "external_id": null,
    "registry_name": null,
    "registry_url": null,
    "serial": "YsGcguF1YMUiTsETrUI",
    "status": "stolen",
    "stolen": true,
    "stolen_coordinates": null,
    "stolen_location": "Jroldm D5px1y, LPAN@PAG.COM, MT",
    "thumb": null,
    "title": "1982 zpoz6o2JZI38p GRDpA5otxkSuQ9PrDT pedi cab (rickshaw)",
    "url": "https://bikeindex.org/bikes/1649169",
    "year": 1982
  },
  {
    "date_stolen": 1693252800,
    "description": "",
    "frame_colors": [
      "Black"
    ],
    "frame_model": "Escape 2 Disc",
    "id": 1015022,
    "is_stock_img": false,
    "large_img": "https://files.bikeindex.org/uploads/Pu/405759/large_573A1001-C26A-4D76-8CE5-7E737F4A89DD.jpeg",
    "location_found": null,
    "manufacturer_name": "Giant",
    "external_id": null,
    "registry_name": null,
    "registry_url": null,
    "serial": "K9EK56232",
    "status": "stolen",
    "stolen": true,
    "stolen_coordinates": [
      39.78,
      -86.17
    ],
    "stolen_location": "Indianapolis, IN 46202, US",
    "thumb": "https://files.bikeindex.org/uploads/Pu/405759/small_573A1001-C26A-4D76-8CE5-7E737F4A89DD.jpeg",
    "title": "2020 Giant Escape 2 Disc",
    "url": "https://bikeindex.org/bikes/1015022",
    "year": 2020
  },
  {
    "date_stolen": 1693252800,
    "description": "black with red frame; dual suspension; 2 by 10; bright red hand grips; hydraulic disc brakes; dropper post",
    "frame_colors": [
      "Black"
    ],
    "frame_model": "Stumpjumper FSR COMP",
    "id": 1649204,
    "is_stock_img": false,
    "large_img": "https://files.bikeindex.org/uploads/Pu/740681/large_brad_bike.jpg",
    "location_found": null,
    "manufacturer_name": "Specialized",
    "external_id": null,
    "registry_name": null,
    "registry_url": null,
    "serial": "WSBC601078908L- (BI 2563)",
    "status": "stolen",
    "stolen": true,
    "stolen_coordinates": [
      51.07,
      -114.1
    ],
    "stolen_location": "Calgary, T2M 1B2, CA",
    "thumb": "https://files.bikeindex.org/uploads/Pu/740681/small_brad_bike.jpg",
    "title": "2016 Specialized Stumpjumper FSR COMP",
    "url": "https://bikeindex.org/bikes/1649204",
    "year": 2016
  },
  {
    "date_stolen": 1693252800,
    "description": "27.5\" wheels; vibrant orange-red frame; dual suspension- Fox fork and rear suspension; white wolf sticker on black fender; black handlebars; dropper post; hydraulic disc brakes",
    "frame_colors": [
      "Red"
    ],
    "frame_model": "Jeffsy",
    "id": 1649184,
    "is_stock_img": false,
    "large_img": "https://files.bikeindex.org/uploads/Pu/740674/large_jess_bike.jpg",
    "location_found": null,
    "manufacturer_name": "YT",
    "external_id": null,
    "registry_name": null,
    "registry_url": null,
    "serial": "V1812CF20133",
    "status": "stolen",
    "stolen": true,
    "stolen_coordinates": [
      51.07,
      -114.1
    ],
    "stolen_location": "Calgary, T2M 1B2, CA",
    "thumb": "https://files.bikeindex.org/uploads/Pu/740674/small_jess_bike.jpg",
    "title": "2019 YT Jeffsy",
    "url": "https://bikeindex.org/bikes/1649184",
    "year": 2019
  },
  {
    "date_stolen": 1693252000,
    "description": "",
    "frame_colors": [
      "Green"
    ],
    "frame_model": "Sirrus",
    "id": 1644762,
    "is_stock_img": false,
    "large_img": null,
    "location_found": null,
    "manufacturer_name": "Specialized",
    "external_id": null,
    "registry_name": null,
    "registry_url": null,
    "serial": "en14764",
    "status": "stolen",
    "stolen": true,
    "stolen_coordinates": null,
    "stolen_location": "US",
    "thumb": null,
    "title": "Specialized Sirrus",
    "url": "https://bikeindex.org/bikes/1644762",
    "year": null
  },
  {
    "date_stolen": 1693251283,
    "description": null,
    "frame_colors": [
      "Yellow or Gold",
      "Orange",
      "Teal"
    ],
    "frame_model": "pzzEFG7CYjmeXhMeh",
    "id": 1649143,
    "is_stock_img": false,
    "large_img": null,
    "location_found": null,
    "manufacturer_name": "G6S2SA5hutr0uYD",
    "external_id": null,
    "registry_name": null,
    "registry_url": null,
    "serial": "ZQjWbHSklE",
    "status": "stolen",
    "stolen": true,
    "stolen_coordinates": null,
    "stolen_location": "Ur2z Njx T Jijw F Fg Z Nl Bf, SUNYAN2008@GMAIL.COM, IQ",
    "thumb": null,
    "title": "2014 G6S2SA5hutr0uYD pzzEFG7CYjmeXhMeh tricycle",
    "url": "https://bikeindex.org/bikes/1649143",
    "year": 2014
  },
  {
    "date_stolen": 1693247400,
    "description": "Black glossy finish. \"Rocky Mountain\" lettering in red on the side of the frame. Greep zip-tie on the middle of the frame along with a Kryptonite lock holder.",
    "frame_colors": [
      "Black",
      "Red"
    ],
    "frame_model": "Hybrid",
    "id": 1649215,
    "is_stock_img": false,
    "large_img": "https://files.bikeindex.org/uploads/Pu/740691/large_IMG-6138.PNG",
    "location_found": null,
    "manufacturer_name": "Rocky Mountain Bicycles",
    "external_id": null,
    "registry_name": null,
    "registry_url": null,
    "serial": "Unknown",
    "status": "stolen",
    "stolen": true,
    "stolen_coordinates": [
      51.07,
      -114.09
    ],
    "stolen_location": "Calgary, T2M 0L4, CA",
    "thumb": "https://files.bikeindex.org/uploads/Pu/740691/small_IMG-6138.PNG",
    "title": "Rocky Mountain Bicycles Hybrid",
    "url": "https://bikeindex.org/bikes/1649215",
    "year": null
  },
  {
    "date_stolen": 1693246021,
    "description": null,
    "frame_colors": [
      "Blue"
    ],
    "frame_model": "Lacuna Pro",
    "id": 1649067,
    "is_stock_img": false,
    "large_img": null,
    "location_found": null,
    "manufacturer_name": "GT Bicycles",
    "external_id": null,
    "registry_name": null,
    "registry_url": null,
    "serial": "gftsd20j3592",
    "status": "stolen",
    "stolen": true,
    "stolen_coordinates": [
      53.44,
      -113.5
    ],
    "stolen_location": "Edmonton, T6J 6G5, CA",
    "thumb": null,
    "title": "GT Bicycles Lacuna Pro",
    "url": "https://bikeindex.org/bikes/1649067",
    "year": null
  },
  {
    "date_stolen": 1693245600,
    "description": "",
    "frame_colors": [
      "Silver, gray or bare metal"
    ],
    "frame_model": "TR 100 RR MTB GREY",
    "id": 1649081,
    "is_stock_img": false,
    "large_img": null,
    "location_found": null,
    "manufacturer_name": "Decathlon",
    "external_id": null,
    "registry_name": null,
    "registry_url": null,
    "serial": "Unknown",
    "status": "stolen",
    "stolen": true,
    "stolen_coordinates": [
      51.25,
      4.5
    ],
    "stolen_location": "Schoten, 2900, BE",
    "thumb": null,
    "title": "2023 Decathlon TR 100 RR MTB GREY",
    "url": "https://bikeindex.org/bikes/1649081",
    "year": 2023
  },
  {
    "date_stolen": 1693242736,
    "description": null,
    "frame_colors": [
      "Purple",
      "Pink",
      "Silver, gray or bare metal"
    ],
    "frame_model": "fnGsOFDwri6o",
    "id": 1649030,
    "is_stock_img": false,
    "large_img": null,
    "location_found": null,
    "manufacturer_name": "xMtFX5fJDJJmOzrHTwV",
    "external_id": null,
    "registry_name": null,
    "registry_url": null,
    "serial": "0vwNKAcwcGpuL",
    "status": "stolen",
    "stolen": true,
    "stolen_coordinates": null,
    "stolen_location": "X Xi Ok Fwm M Ibn8 Ix56 Xi, CREATIVEUNIT@GMAIL.COM, MV",
    "thumb": null,
    "title": "1979 xMtFX5fJDJJmOzrHTwV fnGsOFDwri6o cargo bike (rear storage)",
    "url": "https://bikeindex.org/bikes/1649030",
    "year": 1979
  },
  {
    "date_stolen": 1693242556,
    "description": null,
    "frame_colors": [
      "Black",
      "Black"
    ],
    "frame_model": "CmwBpqoeEVy3iMDo",
    "id": 1649025,
    "is_stock_img": false,
    "large_img": null,
    "location_found": null,
    "manufacturer_name": "Y9tOoMhH7FoyRUVl8",
    "external_id": null,
    "registry_name": null,
    "registry_url": null,
    "serial": "GfV3FCDEK82sDUyl7I",
    "status": "stolen",
    "stolen": true,
    "stolen_coordinates": null,
    "stolen_location": "E8 Bp62ucm Fp Ko Tmu T3, LPAN@PAG.COM, NA",
    "thumb": null,
    "title": "1945 Y9tOoMhH7FoyRUVl8 CmwBpqoeEVy3iMDo e-skateboard (e-unicycle, personal mobility device, etc)",
    "url": "https://bikeindex.org/bikes/1649025",
    "year": 1945
  },
  {
    "date_stolen": 1693242049,
    "description": null,
    "frame_colors": [
      "Black"
    ],
    "frame_model": "fat tire",
    "id": 1575006,
    "is_stock_img": false,
    "large_img": "https://files.bikeindex.org/uploads/Pu/734264/large_IMG_4565.JPG",
    "location_found": null,
    "manufacturer_name": "Northrock",
    "external_id": null,
    "registry_name": null,
    "registry_url": null,
    "serial": "c3ef0044",
    "status": "stolen",
    "stolen": true,
    "stolen_coordinates": null,
    "stolen_location": "US",
    "thumb": "https://files.bikeindex.org/uploads/Pu/734264/small_IMG_4565.JPG",
    "title": "2019 Northrock fat tire",
    "url": "https://bikeindex.org/bikes/1575006",
    "year": 2019
  },
  {
    "date_stolen": 1693242011,
    "description": null,
    "frame_colors": [
      "Red",
      "Yellow or Gold",
      "Pink"
    ],
    "frame_model": "R6YqozuoY1fomu",
    "id": 1649019,
    "is_stock_img": false,
    "large_img": null,
    "location_found": null,
    "manufacturer_name": "q1aKKXerKHRZo",
    "external_id": null,
    "registry_name": null,
    "registry_url": null,
    "serial": "fhEZDSx65cnFXVvGl",
    "status": "stolen",
    "stolen": true,
    "stolen_coordinates": null,
    "stolen_location": "5 S4j4h Tm4 U7dq1 Wl, SILLYMINDYMOO@YAHOO.COM, MR",
    "thumb": null,
    "title": "1901 q1aKKXerKHRZo R6YqozuoY1fomu cargo tricycle (rear storage)",
    "url": "https://bikeindex.org/bikes/1649019",
    "year": 1901
  },
  {
    "date_stolen": 1693242008,
    "description": null,
    "frame_colors": [
      "Red",
      "Yellow or Gold",
      "Pink"
    ],
    "frame_model": "R6YqozuoY1fomu",
    "id": 1649018,
    "is_stock_img": false,
    "large_img": null,
    "location_found": null,
    "manufacturer_name": "q1aKKXerKHRZo",
    "external_id": null,
    "registry_name": null,
    "registry_url": null,
    "serial": "fhEZDSx65cnFXVvGl",
    "status": "stolen",
    "stolen": true,
    "stolen_coordinates": null,
    "stolen_location": "5 S4j4h Tm4 U7dq1 Wl, SILLYMINDYMOO@YAHOO.COM, MR",
    "thumb": null,
    "title": "1901 q1aKKXerKHRZo R6YqozuoY1fomu cargo tricycle (rear storage)",
    "url": "https://bikeindex.org/bikes/1649018",
    "year": 1901
  },
  {
    "date_stolen": 1693242000,
    "description": null,
    "frame_colors": [
      "White",
      "Black"
    ],
    "frame_model": "Growler 40",
    "id": 1649040,
    "is_stock_img": false,
    "large_img": "https://files.bikeindex.org/uploads/Pu/740604/large_IMG_20230828_084821_562.jpg",
    "location_found": null,
    "manufacturer_name": "Rocky Mountain Bicycles",
    "external_id": null,
    "registry_name": null,
    "registry_url": null,
    "serial": "SRMAJ2103667",
    "status": "stolen",
    "stolen": true,
    "stolen_coordinates": [
      51.05,
      -114.1
    ],
    "stolen_location": "Calgary, T3C 1E5, CA",
    "thumb": "https://files.bikeindex.org/uploads/Pu/740604/small_IMG_20230828_084821_562.jpg",
    "title": "2022 Rocky Mountain Bicycles Growler 40",
    "url": "https://bikeindex.org/bikes/1649040",
    "year": 2022
  },
  {
    "date_stolen": 1693239656,
    "description": null,
    "frame_colors": [
      "Red",
      "White"
    ],
    "frame_model": "tsQPotem2fbWbXU",
    "id": 1648985,
    "is_stock_img": false,
    "large_img": null,
    "location_found": null,
    "manufacturer_name": "5E9Rz2MLgyY5",
    "external_id": null,
    "registry_name": null,
    "registry_url": null,
    "serial": "UcE6YydyZpv",
    "status": "stolen",
    "stolen": true,
    "stolen_coordinates": null,
    "stolen_location": "13xc Blmdifl Xv21, PHILLIPTRS@AOL.COM, GR",
    "thumb": null,
    "title": "1959 5E9Rz2MLgyY5 tsQPotem2fbWbXU tricycle",
    "url": "https://bikeindex.org/bikes/1648985",
    "year": 1959
  },
  {
    "date_stolen": 1693239271,
    "description": null,
    "frame_colors": [
      "Blue",
      "Pink"
    ],
    "frame_model": "tMRYhElt6BAnUPT",
    "id": 1648976,
    "is_stock_img": false,
    "large_img": null,
    "location_found": null,
    "manufacturer_name": "w0Q12TIJvxWLYQ1",
    "external_id": null,
    "registry_name": null,
    "registry_url": null,
    "serial": "cGRTEfzHacsBV",
    "status": "stolen",
    "stolen": true,
    "stolen_coordinates": null,
    "stolen_location": "0 Sz Tay3 Q Nwdhi, TAMRAJANE@COMCAST.NET, AR",
    "thumb": null,
    "title": "1971 w0Q12TIJvxWLYQ1 tMRYhElt6BAnUPT tall bike",
    "url": "https://bikeindex.org/bikes/1648976",
    "year": 1971
  },
  {
    "date_stolen": 1693239065,
    "description": null,
    "frame_colors": [
      "White",
      "Silver, gray or bare metal",
      "White"
    ],
    "frame_model": "bSMfWCVh8Up8VGt",
    "id": 1648973,
    "is_stock_img": false,
    "large_img": null,
    "location_found": null,
    "manufacturer_name": "TT10k38SgGwKJB",
    "external_id": null,
    "registry_name": null,
    "registry_url": null,
    "serial": "3ndvfqNzb40Xb5I",
    "status": "stolen",
    "stolen": true,
    "stolen_coordinates": null,
    "stolen_location": "Up Ro3 E1 Td4uo, KELLYLREYNOLDS@HOTMAIL.COM, SL",
    "thumb": null,
    "title": "1969 TT10k38SgGwKJB bSMfWCVh8Up8VGt tall bike",
    "url": "https://bikeindex.org/bikes/1648973",
    "year": 1969
  },
  {
    "date_stolen": 1693238627,
    "description": null,
    "frame_colors": [
      "Pink",
      "Silver, gray or bare metal",
      "Yellow or Gold"
    ],
    "frame_model": "GNqZTsaUIAalJTsZVmP",
    "id": 1648967,
    "is_stock_img": false,
    "large_img": null,
    "location_found": null,
    "manufacturer_name": "FhRlsDo87812O7Jsi",
    "external_id": null,
    "registry_name": null,
    "registry_url": null,
    "serial": "ToChiS6Tp4Zzk3",
    "status": "stolen",
    "stolen": true,
    "stolen_coordinates": null,
    "stolen_location": "T Gs6okh Vk P45al Wa6lou, LPAN@PAG.COM, BE",
    "thumb": null,
    "title": "1941 FhRlsDo87812O7Jsi GNqZTsaUIAalJTsZVmP",
    "url": "https://bikeindex.org/bikes/1648967",
    "year": 1941
  },
  {
    "date_stolen": 1693238400,
    "description": null,
    "frame_colors": [
      "Blue"
    ],
    "frame_model": "Rockhopper Pro Disc All Mountain",
    "id": 1648982,
    "is_stock_img": false,
    "large_img": null,
    "location_found": null,
    "manufacturer_name": "Specialized",
    "external_id": null,
    "registry_name": null,
    "registry_url": null,
    "serial": "Unknown",
    "status": "stolen",
    "stolen": true,
    "stolen_coordinates": [
      42.96,
      -71.44
    ],
    "stolen_location": "Manchester, NH 03103, US",
    "thumb": null,
    "title": "Specialized Rockhopper Pro Disc All Mountain",
    "url": "https://bikeindex.org/bikes/1648982",
    "year": null
  },
  {
    "date_stolen": 1693238400,
    "description": "Black and white with a white marzocchi fork and silver stem and pedals ",
    "frame_colors": [
      "Black",
      "White"
    ],
    "frame_model": "Growler",
    "id": 1648990,
    "is_stock_img": false,
    "large_img": "https://files.bikeindex.org/uploads/Pu/740579/large_20230625_165115.jpg",
    "location_found": null,
    "manufacturer_name": "Rocky Mountain Bicycles",
    "external_id": null,
    "registry_name": null,
    "registry_url": null,
    "serial": "SRMAJ2103667",
    "status": "stolen",
    "stolen": true,
    "stolen_coordinates": [
      51.04,
      -114.1
    ],
    "stolen_location": "Calgary, T2T 4M5, CA",
    "thumb": "https://files.bikeindex.org/uploads/Pu/740579/small_20230625_165115.jpg",
    "title": "2022 Rocky Mountain Bicycles Growler",
    "url": "https://bikeindex.org/bikes/1648990",
    "year": 2022
  },
  {
    "date_stolen": 1693238400,
    "description": "Small scratch on the top tube.",
    "frame_colors": [
      "Black"
    ],
    "frame_model": "XFR 2",
    "id": 1649241,
    "is_stock_img": false,
    "large_img": null,
    "location_found": null,
    "manufacturer_name": "Norco Bikes",
    "external_id": null,
    "registry_name": null,
    "registry_url": null,
    "serial": "1GE31400943",
    "status": "stolen",
    "stolen": true,
    "stolen_coordinates": [
      44.48,
      -73.21
    ],
    "stolen_location": "Burlington, VT 05401, US",
    "thumb": null,
    "title": "2021 Norco Bikes XFR 2",
    "url": "https://bikeindex.org/bikes/1649241",
    "year": 2021
  },
  {
    "date_stolen": 1693238347,
    "description": null,
    "frame_colors": [
      "Green",
      "Purple",
      "Red"
    ],
    "frame_model": "FAjsG0sLqCMGOn",
    "id": 1648965,
    "is_stock_img": false,
    "large_img": null,
    "location_found": null,
    "manufacturer_name": "XFvZlU5benqBLF",
    "external_id": null,
    "registry_name": null,
    "registry_url": null,
    "serial": "xDNyaODPWXhF",
    "status": "stolen",
    "stolen": true,
    "stolen_coordinates": null,
    "stolen_location": "Sx R Mbeq Q4 U Tu Wb, DECI@BELLNET.CA, PR",
    "thumb": null,
    "title": "1983 XFvZlU5benqBLF FAjsG0sLqCMGOn cargo tricycle (front storage)",
    "url": "https://bikeindex.org/bikes/1648965",
    "year": 1983
  },
  {
    "date_stolen": 1693238007,
    "description": null,
    "frame_colors": [
      "Red"
    ],
    "frame_model": null,
    "id": 1648962,
    "is_stock_img": false,
    "large_img": null,
    "location_found": null,
    "manufacturer_name": "Trek",
    "external_id": null,
    "registry_name": null,
    "registry_url": null,
    "serial": "WTU107XC4130T",
    "status": "stolen",
    "stolen": true,
    "stolen_coordinates": [
      42.35,
      -71.06
    ],
    "stolen_location": "Boston, MA 02111, US",
    "thumb": null,
    "title": "Trek",
    "url": "https://bikeindex.org/bikes/1648962",
    "year": null
  },
  {
    "date_stolen": 1693236852,
    "description": null,
    "frame_colors": [
      "Brown",
      "Pink",
      "Silver, gray or bare metal"
    ],
    "frame_model": "8EOCxGn03lYlNrENFjc",
    "id": 1648948,
    "is_stock_img": false,
    "large_img": null,
    "location_found": null,
    "manufacturer_name": "DQMnt9qTml5ATIIgqHP",
    "external_id": null,
    "registry_name": null,
    "registry_url": null,
    "serial": "aJmnMnr4BqFW",
    "status": "stolen",
    "stolen": true,
    "stolen_coordinates": null,
    "stolen_location": "Ipbiqtksvs Za, MARIE.HAAS.94@OUTLOOK.COM, VE",
    "thumb": null,
    "title": "1938 DQMnt9qTml5ATIIgqHP 8EOCxGn03lYlNrENFjc",
    "url": "https://bikeindex.org/bikes/1648948",
    "year": 1938
  },
  {
    "date_stolen": 1693236521,
    "description": null,
    "frame_colors": [
      "Black",
      "Purple",
      "Black"
    ],
    "frame_model": "FDjTnrGEu5FLLgDMI",
    "id": 1648942,
    "is_stock_img": false,
    "large_img": null,
    "location_found": null,
    "manufacturer_name": "V0xjYC7Q874H",
    "external_id": null,
    "registry_name": null,
    "registry_url": null,
    "serial": "Nd0OCxTrE8xALzd5J",
    "status": "stolen",
    "stolen": true,
    "stolen_coordinates": null,
    "stolen_location": "N Fe6lpp6kq, LYNETMRG@GMAIL.COM, AI",
    "thumb": null,
    "title": "2017 V0xjYC7Q874H FDjTnrGEu5FLLgDMI pedi cab (rickshaw)",
    "url": "https://bikeindex.org/bikes/1648942",
    "year": 2017
  },
  {
    "date_stolen": 1693236466,
    "description": null,
    "frame_colors": [
      "Green",
      "Red",
      "Blue"
    ],
    "frame_model": "H9k5IfO26YHllYdZgm",
    "id": 1648939,
    "is_stock_img": false,
    "large_img": null,
    "location_found": null,
    "manufacturer_name": "SIjmvihITGRrT",
    "external_id": null,
    "registry_name": null,
    "registry_url": null,
    "serial": "ehaJJacBx5eE4fgocYtb",
    "status": "stolen",
    "stolen": true,
    "stolen_coordinates": null,
    "stolen_location": "R X63wtx Lta Xunu, LPAN@PAG.COM, GI",
    "thumb": null,
    "title": "1998 SIjmvihITGRrT H9k5IfO26YHllYdZgm unicycle",
    "url": "https://bikeindex.org/bikes/1648939",
    "year": 1998
  },
  {
    "date_stolen": 1693234800,
    "description": null,
    "frame_colors": [
      "Silver, gray or bare metal"
    ],
    "frame_model": "FX1",
    "id": 1644333,
    "is_stock_img": false,
    "large_img": null,
    "location_found": null,
    "manufacturer_name": "Trek",
    "external_id": null,
    "registry_name": null,
    "registry_url": null,
    "serial": "WTU169C0943P",
    "status": "stolen",
    "stolen": true,
    "stolen_coordinates": [
      40.01,
      -105.27
    ],
    "stolen_location": "Boulder, CO, US",
    "thumb": null,
    "title": "2020 Trek FX1",
    "url": "https://bikeindex.org/bikes/1644333",
    "year": 2020
  },
  {
    "date_stolen": 1693233854,
    "description": null,
    "frame_colors": [
      "Brown",
      "Purple",
      "White"
    ],
    "frame_model": "9PSjiVuW3FlZP7EGuv",
    "id": 1648903,
    "is_stock_img": false,
    "large_img": null,
    "location_found": null,
    "manufacturer_name": "qD0YT1T9ONNm",
    "external_id": null,
    "registry_name": null,
    "registry_url": null,
    "serial": "rfnJ098bZ12tk8i2T",
    "status": "stolen",
    "stolen": true,
    "stolen_coordinates": null,
    "stolen_location": "Eznt Q1ey Fe Kg0x8wh, ARCADIANPRIDE@GMAIL.COM, CU",
    "thumb": null,
    "title": "1937 qD0YT1T9ONNm 9PSjiVuW3FlZP7EGuv tandem",
    "url": "https://bikeindex.org/bikes/1648903",
    "year": 1937
  },
  {
    "date_stolen": 1693233234,
    "description": null,
    "frame_colors": [
      "Red"
    ],
    "frame_model": "Rockhopper 27.5 FLORED/WHT",
    "id": 1648895,
    "is_stock_img": false,
    "large_img": null,
    "location_found": null,
    "manufacturer_name": "Specialized",
    "external_id": null,
    "registry_name": null,
    "registry_url": null,
    "serial": "WSBC02600508r7",
    "status": "stolen",
    "stolen": true,
    "stolen_coordinates": [
      39.12,
      -77.16
    ],
    "stolen_location": "Derwood, MD 20855, US",
    "thumb": null,
    "title": "Specialized Rockhopper 27.5 FLORED/WHT",
    "url": "https://bikeindex.org/bikes/1648895",
    "year": null
  },
  {
    "date_stolen": 1693232301,
    "description": null,
    "frame_colors": [
      "Pink",
      "Teal",
      "Purple"
    ],
    "frame_model": "rvLVmWnGMwe",
    "id": 1648879,
    "is_stock_img": false,
    "large_img": null,
    "location_found": null,
    "manufacturer_name": "dpYeR7GJ3OvCYpe",
    "external_id": null,
    "registry_name": null,
    "registry_url": null,
    "serial": "1xseWyuqh0zBP",
    "status": "stolen",
    "stolen": true,
    "stolen_coordinates": null,
    "stolen_location": "Ja F Mh Tkxqli Em V Uk Pc, LPAN@PAG.COM, PS",
    "thumb": null,
    "title": "1933 dpYeR7GJ3OvCYpe rvLVmWnGMwe e-scooter",
    "url": "https://bikeindex.org/bikes/1648879",
    "year": 1933
  },
  {
    "date_stolen": 1693231380,
    "description": null,
    "frame_colors": [
      "Stickers tape or other cover-up",
      "Green",
      "Black"
    ],
    "frame_model": "k6dEnSTIQH",
    "id": 1649008,
    "is_stock_img": false,
    "large_img": null,
    "location_found": null,
    "manufacturer_name": "KABXfuYjkcZaLG6nU",
    "external_id": null,
    "registry_name": null,
    "registry_url": null,
    "serial": "E3KctYLONaEPiW",
    "status": "stolen",
    "stolen": true,
    "stolen_coordinates": null,
    "stolen_location": "Ucq79 Mb A5wr, KODIAK46733@YAHOO.COM, OM",
    "thumb": null,
    "title": "1965 KABXfuYjkcZaLG6nU k6dEnSTIQH stroller",
    "url": "https://bikeindex.org/bikes/1649008",
    "year": 1965
  },
  {
    "date_stolen": 1693231327,
    "description": null,
    "frame_colors": [
      "Black"
    ],
    "frame_model": "Black",
    "id": 1648869,
    "is_stock_img": false,
    "large_img": null,
    "location_found": null,
    "manufacturer_name": "Hey Bike",
    "external_id": null,
    "registry_name": null,
    "registry_url": null,
    "serial": "Unknown",
    "status": "stolen",
    "stolen": true,
    "stolen_coordinates": [
      36,
      -94.09
    ],
    "stolen_location": "Fayetteville, AR 72701, US",
    "thumb": null,
    "title": "2021 Hey Bike Black e-skateboard (e-unicycle, personal mobility device, etc)",
    "url": "https://bikeindex.org/bikes/1648869",
    "year": 2021
  },
  {
    "date_stolen": 1693231200,
    "description": "Bar extension wrapped green foam tape orange spike peddals",
    "frame_colors": [
      "Orange"
    ],
    "frame_model": "",
    "id": 1648884,
    "is_stock_img": false,
    "large_img": "https://files.bikeindex.org/uploads/Pu/740529/large_1000003544.jpg",
    "location_found": null,
    "manufacturer_name": "Dekerf",
    "external_id": null,
    "registry_name": null,
    "registry_url": null,
    "serial": "DEK 1234",
    "status": "stolen",
    "stolen": true,
    "stolen_coordinates": [
      53.47,
      -113.5
    ],
    "stolen_location": "Edmonton, T6J-2L1, CA",
    "thumb": "https://files.bikeindex.org/uploads/Pu/740529/small_1000003544.jpg",
    "title": "1999 Dekerf",
    "url": "https://bikeindex.org/bikes/1648884",
    "year": 1999
  },
  {
    "date_stolen": 1693231200,
    "description": "Green frame, 750W, class 2 Ebike. 2 black baskets , black rims.",
    "frame_colors": [
      "Green"
    ],
    "frame_model": "Rad Runner 2",
    "id": 1239351,
    "is_stock_img": false,
    "large_img": "https://files.bikeindex.org/uploads/Pu/740669/large_20220228_191720.jpg",
    "location_found": null,
    "manufacturer_name": "Rad Power Bikes",
    "external_id": null,
    "registry_name": null,
    "registry_url": null,
    "serial": "VR2H21V2841",
    "status": "stolen",
    "stolen": true,
    "stolen_coordinates": [
      33.78,
      -118.15
    ],
    "stolen_location": "Long Beach, CA 90804, US",
    "thumb": "https://files.bikeindex.org/uploads/Pu/740669/small_20220228_191720.jpg",
    "title": "2022 Rad Power Bikes Rad Runner 2",
    "url": "https://bikeindex.org/bikes/1239351",
    "year": 2022
  },
  {
    "date_stolen": 1693230585,
    "description": null,
    "frame_colors": [
      "Stickers tape or other cover-up",
      "Black",
      "Yellow or Gold"
    ],
    "frame_model": "wKTp9NFLCh9izicym",
    "id": 1648858,
    "is_stock_img": false,
    "large_img": null,
    "location_found": null,
    "manufacturer_name": "ZV8b3vQbSX8wr4",
    "external_id": null,
    "registry_name": null,
    "registry_url": null,
    "serial": "4hQCoztbXaxkS",
    "status": "stolen",
    "stolen": true,
    "stolen_coordinates": null,
    "stolen_location": "Dq69ifo P Ck Zfh Eweq Jmg, SMVS.SN66@GMAIL.COM, PS",
    "thumb": null,
    "title": "1993 ZV8b3vQbSX8wr4 wKTp9NFLCh9izicym penny farthing",
    "url": "https://bikeindex.org/bikes/1648858",
    "year": 1993
  },
  {
    "date_stolen": 1693225800,
    "description": null,
    "frame_colors": [
      "Green"
    ],
    "frame_model": "Stumpjumper",
    "id": 1649587,
    "is_stock_img": false,
    "large_img": "https://files.bikeindex.org/uploads/Pu/740875/large_IMG_2509.jpeg",
    "location_found": null,
    "manufacturer_name": "Specialized",
    "external_id": null,
    "registry_name": null,
    "registry_url": null,
    "serial": "Unknown",
    "status": "stolen",
    "stolen": true,
    "stolen_coordinates": [
      45.59,
      -122.69
    ],
    "stolen_location": "Portland, OR 97217, US",
    "thumb": "https://files.bikeindex.org/uploads/Pu/740875/small_IMG_2509.jpeg",
    "title": "1997 Specialized Stumpjumper",
    "url": "https://bikeindex.org/bikes/1649587",
    "year": 1997
  }
]
